core/__init__.py
core/models.py
core/utils.py
bubbletea-0.0.2.dist-info/LICENSE
bubbletea-0.0.2.dist-info/METADATA
bubbletea-0.0.2.dist-info/WHEEL
bubbletea-0.0.2.dist-info/top_level.txt
bubbletea-0.0.2.dist-info/RECORD
