Metadata-Version: 2.1
Name: bubbletea
Version: 0.0.2
Summary: Python library for creating history-augmented interactive medical chatbots with tabular embedding alignment (TEA)
Home-page: https://github.com/doerlbh/bubbletea
Author: Baihan Lin
Author-email: doerlbh@gmail.com
License: GPLv3
Project-URL: Bug Tracker, https://github.com/doerlbh/bubbletea/issues
Classifier: Programming Language :: Python :: 3
Classifier: License :: OSI Approved :: GNU General Public License v3 (GPLv3)
Classifier: Operating System :: OS Independent
Requires-Python: >=3.6
License-File: LICENSE
Requires-Dist: numpy (>=1.16.5)
Requires-Dist: pandas
